[
	{
		"id": 1,
		"area": "EQ",
		"time": "2021-12-15 03:20:24",
		"building": "Ingersoll Hall/Ext",
		"total": 1,
		"desc": "Small and gray",
		"action": "Roaming around"
	},
	{
		"id": 2,
		"area": "EQ",
		"time": "2020-01-16 19:16:21",
		"building": "Clarie Tow Center",
		"total": 4,
		"desc": "Medium and gray",
		"action": "Searching in trash can"
	},
	{
		"id": 3,
		"area": "EQ",
		"time": "2022-11-14 05:20:06",
		"building": "Whitehead Hall",
		"total": 5,
		"desc": "Large and brown",
		"action": "Climbing tree"
	},
	{
		"id": 4,
		"area": "WQ",
		"time": "2019-02-04 15:47:47",
		"building": "Roosevelt Hall/Ext",
		"total": 5,
		"desc": "Large and brown",
		"action": "Climbing tree"
	},
	{
		"id": 5,
		"area": "EQ",
		"time": "2021-04-15 01:21:05",
		"building": "Clarie Tow Center",
		"total": 2,
		"desc": "Small and brown",
		"action": "Climbing tree"
	},
	{
		"id": 6,
		"area": "OC",
		"time": "2021-07-03 06:30:53",
		"building": "Student Center",
		"total": 5,
		"desc": "Large and gray",
		"action": "Climbing tree"
	},
	{
		"id": 7,
		"area": "WQ",
		"time": "2020-10-13 17:24:58",
		"building": "Roosevelt Hall/Ext",
		"total": 3,
		"desc": "Large and gray",
		"action": "Roaming around"
	},
	{
		"id": 8,
		"area": "EQ",
		"time": "2018-05-26 17:17:36",
		"building": "Boylan Hall",
		"total": 2,
		"desc": "Medium and gray",
		"action": "Searching in trash can"
	},
	{
		"id": 9,
		"area": "EQ",
		"time": "2021-02-27 04:01:39",
		"building": "Boylan Hall",
		"total": 2,
		"desc": "Large and gray",
		"action": "Climbing tree"
	},
	{
		"id": 10,
		"area": "EQ",
		"time": "2021-09-08 04:31:06",
		"building": "Boylan Hall",
		"total": 2,
		"desc": "Medium and brown",
		"action": "Searching in trash can"
	},
	{
		"id": 11,
		"area": "WQ",
		"time": "2020-05-04 17:53:20",
		"building": "West End Building (WEB)",
		"total": 5,
		"desc": "Large and brown",
		"action": "Roaming around"
	},
	{
		"id": 12,
		"area": "OC",
		"time": "2022-12-17 12:36:53",
		"building": "Tanger Hillel House",
		"total": 1,
		"desc": "Large and brown",
		"action": "Searching in trash can"
	},
	{
		"id": 13,
		"area": "WQ",
		"time": "2022-08-07 03:45:04",
		"building": "West Quad Building",
		"total": 3,
		"desc": "Large and gray",
		"action": "Roaming around"
	},
	{
		"id": 14,
		"area": "WQ",
		"time": "2019-10-12 02:20:43",
		"building": "West End Building (WEB)",
		"total": 3,
		"desc": "Medium and brown",
		"action": "Climbing tree"
	},
	{
		"id": 15,
		"area": "OC",
		"time": "2018-08-28 02:39:45",
		"building": "Tanger Hillel House",
		"total": 4,
		"desc": "Medium and brown",
		"action": "Roaming around"
	},
	{
		"id": 16,
		"area": "EQ",
		"time": "2020-12-23 15:21:33",
		"building": "Boylan Hall",
		"total": 3,
		"desc": "Large and brown",
		"action": "Searching in trash can"
	},
	{
		"id": 17,
		"area": "EQ",
		"time": "2022-10-05 14:10:59",
		"building": "Clarie Tow Center",
		"total": 4,
		"desc": "Small and brown",
		"action": "Roaming around"
	},
	{
		"id": 18,
		"area": "WQ",
		"time": "2021-08-03 21:03:01",
		"building": "James Hall",
		"total": 5,
		"desc": "Large and brown",
		"action": "Climbing tree"
	},
	{
		"id": 19,
		"area": "EQ",
		"time": "2022-11-01 15:42:06",
		"building": "Whitehead Hall",
		"total": 3,
		"desc": "Large and brown",
		"action": "Climbing tree"
	},
	{
		"id": 20,
		"area": "EQ",
		"time": "2018-05-20 10:21:21",
		"building": "Library",
		"total": 4,
		"desc": "Small and gray",
		"action": "Roaming around"
	},
	{
		"id": 21,
		"area": "WQ",
		"time": "2021-03-10 10:19:59",
		"building": "West End Building (WEB)",
		"total": 2,
		"desc": "Large and brown",
		"action": "Climbing tree"
	},
	{
		"id": 22,
		"area": "OC",
		"time": "2020-08-01 01:32:17",
		"building": "Tanger Hillel House",
		"total": 1,
		"desc": "Small and brown",
		"action": "Searching in trash can"
	},
	{
		"id": 23,
		"area": "WQ",
		"time": "2022-06-28 21:41:46",
		"building": "West End Building (WEB)",
		"total": 2,
		"desc": "Medium and gray",
		"action": "Searching in trash can"
	},
	{
		"id": 24,
		"area": "WQ",
		"time": "2021-08-13 04:20:50",
		"building": "West Quad Building",
		"total": 1,
		"desc": "Small and gray",
		"action": "Roaming around"
	},
	{
		"id": 25,
		"area": "OC",
		"time": "2019-07-26 08:26:24",
		"building": "Tanger Hillel House",
		"total": 5,
		"desc": "Small and gray",
		"action": "Searching in trash can"
	},
	{
		"id": 26,
		"area": "OC",
		"time": "2019-06-21 11:36:40",
		"building": "Student Center",
		"total": 1,
		"desc": "Medium and gray",
		"action": "Climbing tree"
	},
	{
		"id": 27,
		"area": "OC",
		"time": "2018-04-11 08:59:56",
		"building": "Tanger Hillel House",
		"total": 2,
		"desc": "Large and brown",
		"action": "Climbing tree"
	},
	{
		"id": 28,
		"area": "OC",
		"time": "2022-04-07 05:06:05",
		"building": "Tanger Hillel House",
		"total": 5,
		"desc": "Large and brown",
		"action": "Searching in trash can"
	},
	{
		"id": 29,
		"area": "EQ",
		"time": "2020-05-09 03:39:53",
		"building": "Library",
		"total": 4,
		"desc": "Large and gray",
		"action": "Searching in trash can"
	},
	{
		"id": 30,
		"area": "WQ",
		"time": "2018-02-04 12:54:48",
		"building": "West Quad Building",
		"total": 4,
		"desc": "Small and brown",
		"action": "Roaming around"
	},
	{
		"id": 31,
		"area": "WQ",
		"time": "2022-08-07 13:05:43",
		"building": "James Hall",
		"total": 5,
		"desc": "Medium and gray",
		"action": "Roaming around"
	},
	{
		"id": 32,
		"area": "OC",
		"time": "2022-07-01 06:21:27",
		"building": "Student Center",
		"total": 5,
		"desc": "Small and gray",
		"action": "Searching in trash can"
	},
	{
		"id": 33,
		"area": "OC",
		"time": "2022-08-28 17:39:27",
		"building": "Student Center",
		"total": 4,
		"desc": "Medium and gray",
		"action": "Roaming around"
	},
	{
		"id": 34,
		"area": "WQ",
		"time": "2020-02-12 06:50:59",
		"building": "West End Building (WEB)",
		"total": 1,
		"desc": "Medium and gray",
		"action": "Searching in trash can"
	},
	{
		"id": 35,
		"area": "WQ",
		"time": "2018-08-05 22:31:48",
		"building": "West Quad Building",
		"total": 3,
		"desc": "Small and brown",
		"action": "Climbing tree"
	},
	{
		"id": 36,
		"area": "OC",
		"time": "2022-03-12 11:58:18",
		"building": "Tanger Hillel House",
		"total": 3,
		"desc": "Small and gray",
		"action": "Searching in trash can"
	},
	{
		"id": 37,
		"area": "WQ",
		"time": "2022-12-05 23:44:42",
		"building": "James Hall",
		"total": 4,
		"desc": "Small and brown",
		"action": "Searching in trash can"
	},
	{
		"id": 38,
		"area": "OC",
		"time": "2020-02-19 15:41:42",
		"building": "Tanger Hillel House",
		"total": 5,
		"desc": "Large and gray",
		"action": "Searching in trash can"
	},
	{
		"id": 39,
		"area": "EQ",
		"time": "2022-05-02 07:55:08",
		"building": "Clarie Tow Center",
		"total": 4,
		"desc": "Large and brown",
		"action": "Roaming around"
	},
	{
		"id": 40,
		"area": "OC",
		"time": "2020-08-01 20:33:16",
		"building": "Student Center",
		"total": 1,
		"desc": "Medium and gray",
		"action": "Climbing tree"
	},
	{
		"id": 41,
		"area": "EQ",
		"time": "2020-05-21 03:33:12",
		"building": "Boylan Hall",
		"total": 5,
		"desc": "Small and brown",
		"action": "Roaming around"
	},
	{
		"id": 42,
		"area": "OC",
		"time": "2020-08-07 08:27:56",
		"building": "Student Center",
		"total": 2,
		"desc": "Medium and gray",
		"action": "Climbing tree"
	},
	{
		"id": 43,
		"area": "OC",
		"time": "2020-07-17 03:44:50",
		"building": "Tanger Hillel House",
		"total": 1,
		"desc": "Small and brown",
		"action": "Searching in trash can"
	},
	{
		"id": 44,
		"area": "EQ",
		"time": "2021-08-02 07:07:34",
		"building": "Whitehead Hall",
		"total": 2,
		"desc": "Medium and brown",
		"action": "Searching in trash can"
	},
	{
		"id": 45,
		"area": "OC",
		"time": "2020-05-06 06:55:17",
		"building": "Student Center",
		"total": 1,
		"desc": "Medium and brown",
		"action": "Searching in trash can"
	},
	{
		"id": 46,
		"area": "OC",
		"time": "2018-12-10 04:11:40",
		"building": "Student Center",
		"total": 4,
		"desc": "Medium and brown",
		"action": "Searching in trash can"
	},
	{
		"id": 47,
		"area": "OC",
		"time": "2019-09-05 09:32:21",
		"building": "Tanger Hillel House",
		"total": 4,
		"desc": "Medium and brown",
		"action": "Climbing tree"
	},
	{
		"id": 48,
		"area": "OC",
		"time": "2019-12-20 23:28:46",
		"building": "Tanger Hillel House",
		"total": 2,
		"desc": "Large and gray",
		"action": "Roaming around"
	},
	{
		"id": 49,
		"area": "WQ",
		"time": "2021-12-07 05:05:19",
		"building": "West Quad Building",
		"total": 1,
		"desc": "Large and gray",
		"action": "Roaming around"
	},
	{
		"id": 50,
		"area": "OC",
		"time": "2021-07-15 09:15:18",
		"building": "Student Center",
		"total": 3,
		"desc": "Large and brown",
		"action": "Climbing tree"
	},
	{
		"id": 51,
		"area": "OC",
		"time": "2018-07-12 08:20:12",
		"building": "Tanger Hillel House",
		"total": 2,
		"desc": "Large and brown",
		"action": "Searching in trash can"
	},
	{
		"id": 52,
		"area": "WQ",
		"time": "2019-07-18 23:16:01",
		"building": "James Hall",
		"total": 1,
		"desc": "Small and gray",
		"action": "Roaming around"
	},
	{
		"id": 53,
		"area": "OC",
		"time": "2018-06-14 11:50:08",
		"building": "Student Center",
		"total": 2,
		"desc": "Large and brown",
		"action": "Roaming around"
	},
	{
		"id": 54,
		"area": "OC",
		"time": "2018-01-02 17:59:55",
		"building": "Student Center",
		"total": 4,
		"desc": "Medium and brown",
		"action": "Roaming around"
	},
	{
		"id": 55,
		"area": "WQ",
		"time": "2019-12-17 18:29:15",
		"building": "West End Building (WEB)",
		"total": 3,
		"desc": "Small and brown",
		"action": "Climbing tree"
	},
	{
		"id": 56,
		"area": "WQ",
		"time": "2021-12-23 21:12:06",
		"building": "West Quad Building",
		"total": 5,
		"desc": "Small and brown",
		"action": "Climbing tree"
	},
	{
		"id": 57,
		"area": "EQ",
		"time": "2019-08-16 11:31:26",
		"building": "Clarie Tow Center",
		"total": 1,
		"desc": "Small and brown",
		"action": "Climbing tree"
	},
	{
		"id": 58,
		"area": "WQ",
		"time": "2018-06-15 14:51:20",
		"building": "West Quad Building",
		"total": 1,
		"desc": "Large and gray",
		"action": "Climbing tree"
	},
	{
		"id": 59,
		"area": "OC",
		"time": "2022-01-10 15:19:27",
		"building": "Student Center",
		"total": 2,
		"desc": "Large and gray",
		"action": "Roaming around"
	},
	{
		"id": 60,
		"area": "EQ",
		"time": "2021-07-03 18:02:20",
		"building": "Ingersoll Hall/Ext",
		"total": 3,
		"desc": "Large and brown",
		"action": "Searching in trash can"
	},
	{
		"id": 61,
		"area": "OC",
		"time": "2019-11-22 14:15:32",
		"building": "Student Center",
		"total": 1,
		"desc": "Large and gray",
		"action": "Climbing tree"
	},
	{
		"id": 62,
		"area": "OC",
		"time": "2020-01-24 21:29:11",
		"building": "Student Center",
		"total": 2,
		"desc": "Medium and gray",
		"action": "Roaming around"
	},
	{
		"id": 63,
		"area": "WQ",
		"time": "2021-07-28 15:28:38",
		"building": "Roosevelt Hall/Ext",
		"total": 3,
		"desc": "Medium and gray",
		"action": "Searching in trash can"
	},
	{
		"id": 64,
		"area": "EQ",
		"time": "2021-07-13 22:36:41",
		"building": "Library",
		"total": 4,
		"desc": "Small and brown",
		"action": "Searching in trash can"
	},
	{
		"id": 65,
		"area": "OC",
		"time": "2021-02-11 20:27:37",
		"building": "Tanger Hillel House",
		"total": 3,
		"desc": "Medium and gray",
		"action": "Climbing tree"
	},
	{
		"id": 66,
		"area": "OC",
		"time": "2021-08-26 01:38:09",
		"building": "Tanger Hillel House",
		"total": 5,
		"desc": "Medium and brown",
		"action": "Searching in trash can"
	},
	{
		"id": 67,
		"area": "EQ",
		"time": "2020-11-12 17:30:31",
		"building": "Whitehead Hall",
		"total": 5,
		"desc": "Small and brown",
		"action": "Climbing tree"
	},
	{
		"id": 68,
		"area": "OC",
		"time": "2019-01-10 18:41:08",
		"building": "Student Center",
		"total": 4,
		"desc": "Large and brown",
		"action": "Searching in trash can"
	},
	{
		"id": 69,
		"area": "EQ",
		"time": "2020-10-05 19:11:32",
		"building": "Boylan Hall",
		"total": 5,
		"desc": "Large and gray",
		"action": "Climbing tree"
	},
	{
		"id": 70,
		"area": "OC",
		"time": "2018-06-09 10:38:47",
		"building": "Student Center",
		"total": 2,
		"desc": "Medium and brown",
		"action": "Roaming around"
	},
	{
		"id": 71,
		"area": "OC",
		"time": "2018-02-20 04:24:21",
		"building": "Tanger Hillel House",
		"total": 5,
		"desc": "Medium and brown",
		"action": "Roaming around"
	},
	{
		"id": 72,
		"area": "EQ",
		"time": "2020-06-16 07:42:24",
		"building": "Library",
		"total": 5,
		"desc": "Medium and brown",
		"action": "Climbing tree"
	},
	{
		"id": 73,
		"area": "OC",
		"time": "2020-08-09 06:22:31",
		"building": "Student Center",
		"total": 1,
		"desc": "Small and brown",
		"action": "Climbing tree"
	},
	{
		"id": 74,
		"area": "EQ",
		"time": "2020-02-20 23:14:00",
		"building": "Boylan Hall",
		"total": 1,
		"desc": "Large and gray",
		"action": "Searching in trash can"
	},
	{
		"id": 75,
		"area": "OC",
		"time": "2018-02-02 23:47:17",
		"building": "Tanger Hillel House",
		"total": 1,
		"desc": "Medium and gray",
		"action": "Roaming around"
	},
	{
		"id": 76,
		"area": "OC",
		"time": "2022-05-20 03:15:46",
		"building": "Tanger Hillel House",
		"total": 1,
		"desc": "Large and brown",
		"action": "Roaming around"
	},
	{
		"id": 77,
		"area": "OC",
		"time": "2020-07-15 19:57:10",
		"building": "Tanger Hillel House",
		"total": 5,
		"desc": "Large and gray",
		"action": "Searching in trash can"
	},
	{
		"id": 78,
		"area": "OC",
		"time": "2021-02-14 17:12:47",
		"building": "Student Center",
		"total": 2,
		"desc": "Large and brown",
		"action": "Climbing tree"
	},
	{
		"id": 79,
		"area": "OC",
		"time": "2022-11-28 14:28:31",
		"building": "Student Center",
		"total": 5,
		"desc": "Large and gray",
		"action": "Searching in trash can"
	},
	{
		"id": 80,
		"area": "OC",
		"time": "2020-10-08 23:59:11",
		"building": "Student Center",
		"total": 1,
		"desc": "Large and gray",
		"action": "Roaming around"
	},
	{
		"id": 81,
		"area": "OC",
		"time": "2022-07-05 05:25:44",
		"building": "Student Center",
		"total": 4,
		"desc": "Medium and gray",
		"action": "Roaming around"
	},
	{
		"id": 82,
		"area": "WQ",
		"time": "2019-10-03 13:38:00",
		"building": "James Hall",
		"total": 3,
		"desc": "Large and brown",
		"action": "Roaming around"
	},
	{
		"id": 83,
		"area": "OC",
		"time": "2020-07-01 04:57:27",
		"building": "Student Center",
		"total": 2,
		"desc": "Large and brown",
		"action": "Searching in trash can"
	},
	{
		"id": 84,
		"area": "EQ",
		"time": "2021-02-21 04:04:39",
		"building": "Clarie Tow Center",
		"total": 4,
		"desc": "Medium and brown",
		"action": "Searching in trash can"
	},
	{
		"id": 85,
		"area": "EQ",
		"time": "2019-10-20 13:20:42",
		"building": "Whitehead Hall",
		"total": 1,
		"desc": "Large and gray",
		"action": "Climbing tree"
	},
	{
		"id": 86,
		"area": "EQ",
		"time": "2021-08-22 17:39:01",
		"building": "Boylan Hall",
		"total": 4,
		"desc": "Large and brown",
		"action": "Searching in trash can"
	},
	{
		"id": 87,
		"area": "WQ",
		"time": "2018-06-25 19:15:08",
		"building": "West Quad Building",
		"total": 4,
		"desc": "Small and gray",
		"action": "Searching in trash can"
	},
	{
		"id": 88,
		"area": "EQ",
		"time": "2019-05-12 01:49:51",
		"building": "Ingersoll Hall/Ext",
		"total": 2,
		"desc": "Large and gray",
		"action": "Climbing tree"
	},
	{
		"id": 89,
		"area": "WQ",
		"time": "2018-07-24 03:34:20",
		"building": "James Hall",
		"total": 3,
		"desc": "Medium and gray",
		"action": "Roaming around"
	},
	{
		"id": 90,
		"area": "WQ",
		"time": "2019-06-05 05:39:34",
		"building": "James Hall",
		"total": 1,
		"desc": "Large and gray",
		"action": "Climbing tree"
	},
	{
		"id": 91,
		"area": "EQ",
		"time": "2022-03-13 17:43:05",
		"building": "Ingersoll Hall/Ext",
		"total": 1,
		"desc": "Medium and brown",
		"action": "Searching in trash can"
	},
	{
		"id": 92,
		"area": "WQ",
		"time": "2019-10-21 17:02:43",
		"building": "Roosevelt Hall/Ext",
		"total": 3,
		"desc": "Medium and gray",
		"action": "Roaming around"
	},
	{
		"id": 93,
		"area": "WQ",
		"time": "2018-06-07 14:26:52",
		"building": "James Hall",
		"total": 1,
		"desc": "Medium and gray",
		"action": "Climbing tree"
	},
	{
		"id": 94,
		"area": "OC",
		"time": "2021-12-08 22:54:24",
		"building": "Tanger Hillel House",
		"total": 5,
		"desc": "Large and brown",
		"action": "Climbing tree"
	},
	{
		"id": 95,
		"area": "WQ",
		"time": "2018-09-13 13:39:19",
		"building": "James Hall",
		"total": 1,
		"desc": "Large and brown",
		"action": "Searching in trash can"
	},
	{
		"id": 96,
		"area": "OC",
		"time": "2022-01-23 03:44:06",
		"building": "Student Center",
		"total": 1,
		"desc": "Large and gray",
		"action": "Climbing tree"
	},
	{
		"id": 97,
		"area": "WQ",
		"time": "2020-04-19 14:17:31",
		"building": "West Quad Building",
		"total": 2,
		"desc": "Large and brown",
		"action": "Climbing tree"
	},
	{
		"id": 98,
		"area": "EQ",
		"time": "2019-04-23 05:32:58",
		"building": "Clarie Tow Center",
		"total": 5,
		"desc": "Medium and brown",
		"action": "Climbing tree"
	},
	{
		"id": 99,
		"area": "EQ",
		"time": "2022-10-13 10:00:07",
		"building": "Boylan Hall",
		"total": 2,
		"desc": "Small and brown",
		"action": "Climbing tree"
	},
	{
		"id": 100,
		"area": "OC",
		"time": "2019-04-27 02:33:44",
		"building": "Student Center",
		"total": 5,
		"desc": "Large and brown",
		"action": "Climbing tree"
	}
]
